odoo/addons/base_tier_validation_report/README.rst
odoo/addons/base_tier_validation_report/__init__.py
odoo/addons/base_tier_validation_report/__manifest__.py
odoo/addons/base_tier_validation_report/i18n/base_tier_validation_report.pot
odoo/addons/base_tier_validation_report/i18n/it.po
odoo/addons/base_tier_validation_report/models/__init__.py
odoo/addons/base_tier_validation_report/models/tier_review.py
odoo/addons/base_tier_validation_report/readme/CONTRIBUTORS.rst
odoo/addons/base_tier_validation_report/readme/DESCRIPTION.rst
odoo/addons/base_tier_validation_report/reports/tier_review_report.xml
odoo/addons/base_tier_validation_report/security/groups.xml
odoo/addons/base_tier_validation_report/static/description/icon.png
odoo/addons/base_tier_validation_report/static/description/index.html
odoo_addon_base_tier_validation_report-16.0.1.0.1.5.dist-info/METADATA
odoo_addon_base_tier_validation_report-16.0.1.0.1.5.dist-info/WHEEL
odoo_addon_base_tier_validation_report-16.0.1.0.1.5.dist-info/top_level.txt
odoo_addon_base_tier_validation_report-16.0.1.0.1.5.dist-info/RECORD
